static_templates/__init__.py
static_templates/renderer.py
static_templates/management/__init__.py
static_templates/management/commands/__init__.py
static_templates/management/commands/render_static_templates.py
django_static_templates-0.0.3.dist-info/LICENSE.rst
django_static_templates-0.0.3.dist-info/METADATA
django_static_templates-0.0.3.dist-info/WHEEL
django_static_templates-0.0.3.dist-info/top_level.txt
django_static_templates-0.0.3.dist-info/RECORD
