Metadata-Version: 2.1
Name: django-static-templates
Version: 0.0.3
Summary: django-static-templates provides a management command to render Django templats as static files.
Home-page: https://github.com/moccu/django-static-templates
Author: Moccu GmbH & Co. KG
Author-email: info@moccu.com
License: UNKNOWN
Project-URL: Bug Reports, https://github.com/moccu/django-static-templates/issues
Project-URL: Source, https://github.com/moccu/django-static-templates
Keywords: django static templates
Platform: UNKNOWN
Classifier: Development Status :: 4 - Beta
Classifier: Environment :: Web Environment
Classifier: Framework :: Django
Classifier: Intended Audience :: Developers
Classifier: License :: OSI Approved :: MIT License
Classifier: Programming Language :: Python :: 3
Classifier: Programming Language :: Python :: 3.6
